lut_maker/__init__.py
lut_maker/cli.py
lut_maker/compute.py
lut_maker/constants.py
lut_maker/generate.py
lut_maker/lut.py
lut_maker-0.1.1.dist-info/DESCRIPTION.rst
lut_maker-0.1.1.dist-info/METADATA
lut_maker-0.1.1.dist-info/RECORD
lut_maker-0.1.1.dist-info/WHEEL
lut_maker-0.1.1.dist-info/entry_points.txt
lut_maker-0.1.1.dist-info/metadata.json
lut_maker-0.1.1.dist-info/top_level.txt
