Metadata-Version: 2.0
Name: lut-maker
Version: 0.1.1
Summary: Generate 3D color LUTs in Adobe Cube and Pseudo-3D texture format
Home-page: https://github.com/faymontage/lut-maker
Author: Fay Montage
Author-email: accounts@faymontage.com
License: MIT
Platform: UNKNOWN
Requires-Dist: Pillow
Requires-Dist: click
Requires-Dist: numpy
